owmeta_core/__init__.py
owmeta_core/agg_store.py
owmeta_core/bittorrent.py
owmeta_core/bundle_dependency_store.py
owmeta_core/capabilities.py
owmeta_core/capability.py
owmeta_core/cli.py
owmeta_core/cli_command_wrapper.py
owmeta_core/cli_common.py
owmeta_core/cli_hints.py
owmeta_core/collections.py
owmeta_core/command.py
owmeta_core/command_util.py
owmeta_core/configure.py
owmeta_core/context.py
owmeta_core/context_common.py
owmeta_core/context_dataobject.py
owmeta_core/context_mapped_class_util.py
owmeta_core/context_store.py
owmeta_core/contextualize.py
owmeta_core/custom_dataobject_property.py
owmeta_core/data.py
owmeta_core/dataobject.py
owmeta_core/dataobject_property.py
owmeta_core/datasource.py
owmeta_core/datasource_loader.py
owmeta_core/default.conf
owmeta_core/docscrape.py
owmeta_core/file_lock.py
owmeta_core/file_match.py
owmeta_core/file_utils.py
owmeta_core/git_repo.py
owmeta_core/graph_object.py
owmeta_core/graph_serialization.py
owmeta_core/identifier_mixin.py
owmeta_core/import_contextualizer.py
owmeta_core/import_override.py
owmeta_core/inverse_property.py
owmeta_core/mapped_class.py
owmeta_core/mapper.py
owmeta_core/migrate.py
owmeta_core/module_recorder.py
owmeta_core/project.py
owmeta_core/property_mixins.py
owmeta_core/property_value.py
owmeta_core/quantity.py
owmeta_core/ranged_objects.py
owmeta_core/rdf_go_modifiers.py
owmeta_core/rdf_query_util.py
owmeta_core/rdf_type_resolver.py
owmeta_core/rdf_utils.py
owmeta_core/statement.py
owmeta_core/text_util.py
owmeta_core/utils.py
owmeta_core/variable.py
owmeta_core/bundle/__init__.py
owmeta_core/bundle/archive.py
owmeta_core/bundle/common.py
owmeta_core/bundle/exceptions.py
owmeta_core/bundle/loaders/__init__.py
owmeta_core/bundle/loaders/http.py
owmeta_core/bundle/loaders/sftp.py
owmeta_core/commands/__init__.py
owmeta_core/commands/bundle.py
owmeta_core/data_trans/__init__.py
owmeta_core/data_trans/common_data.py
owmeta_core/data_trans/context_datasource.py
owmeta_core/data_trans/csv_ds.py
owmeta_core-0.13.5.dist-info/LICENSE.txt
owmeta_core-0.13.5.dist-info/METADATA
owmeta_core-0.13.5.dist-info/WHEEL
owmeta_core-0.13.5.dist-info/entry_points.txt
owmeta_core-0.13.5.dist-info/top_level.txt
owmeta_core-0.13.5.dist-info/RECORD
